yacore/__init__.py
yacore/executors.py
yacore/injector.py
yacore/version.txt
yacore/db/__init__.py
yacore/db/postgresql/__init__.py
yacore/db/postgresql/fixtures.py
yacore/db/postgresql/postgresql.py
yacore/log/__init__.py
yacore/log/loguru.py
yacore/log/stdlib.py
yacore/net/__init__.py
yacore/net/http/__init__.py
yacore/net/http/client.py
yacore/net/http/server.py
yacore-0.4.0.dist-info/METADATA
yacore-0.4.0.dist-info/WHEEL
yacore-0.4.0.dist-info/entry_points.txt
yacore-0.4.0.dist-info/license.txt
yacore-0.4.0.dist-info/top_level.txt
yacore-0.4.0.dist-info/RECORD
