Metadata-Version: 2.1
Name: yacore
Version: 0.4.0
Summary: yet another core library
Home-page: https://github.com/pohmelie/yacore
Author: pohmelie
Author-email: multisosnooley@gmail.com
License: MIT
Classifier: Programming Language :: Python
Classifier: Programming Language :: Python :: 3
Requires-Python: >= 3.11
License-File: license.txt
Requires-Dist: cock (>=0.11.0)
Requires-Dist: facet (>=0.9.1)
Requires-Dist: giveme
Provides-Extra: db.postgresql
Requires-Dist: asyncpg ; extra == 'db.postgresql'
Requires-Dist: yarl ; extra == 'db.postgresql'
Provides-Extra: dev
Requires-Dist: pytest-cov ; extra == 'dev'
Requires-Dist: async-timeout ; extra == 'dev'
Requires-Dist: pytest ; extra == 'dev'
Requires-Dist: loguru ; extra == 'dev'
Requires-Dist: ruff ; extra == 'dev'
Requires-Dist: yarl ; extra == 'dev'
Requires-Dist: httpx ; extra == 'dev'
Requires-Dist: asyncpg ; extra == 'dev'
Requires-Dist: pytest-asyncio ; extra == 'dev'
Requires-Dist: hypercorn ; extra == 'dev'
Requires-Dist: pyyaml ; extra == 'dev'
Requires-Dist: testcontainers ; extra == 'dev'
Requires-Dist: fastapi (>=0.89.0) ; extra == 'dev'
Provides-Extra: log.loguru
Requires-Dist: loguru ; extra == 'log.loguru'
Provides-Extra: log.std
Requires-Dist: pyyaml ; extra == 'log.std'
Provides-Extra: net.http
Requires-Dist: async-timeout ; extra == 'net.http'
Requires-Dist: fastapi (>=0.89.0) ; extra == 'net.http'
Requires-Dist: httpx ; extra == 'net.http'
Requires-Dist: hypercorn ; extra == 'net.http'
Requires-Dist: yarl ; extra == 'net.http'
